parc_checker_core/action.py
parc_checker_core/document_checker.py
parc_checker_core/parc_checker_core.py
parc_checker_core/checkers/__init__.py
parc_checker_core/checkers/field_exists_checker.py
parc_checker_core/checkers/field_has_value_checker.py
parc_checker_core/checkers/field_value_checker.py
parc_checker_core/checkers/property_array_value_size_checker.py
parc_checker_core/checkers/property_exists_checker.py
parc_checker_core/checkers/property_has_non_empty_array_value_checker.py
parc_checker_core/checkers/property_has_non_empty_value_checker.py
parc_checker_core/checkers/property_has_value_equals_to_checker.py
parc_checker_core/doc_types/CapAgreement.py
parc_checker_core/doc_types/CommercialFX.py
parc_checker_core-1.2.dist-info/METADATA
parc_checker_core-1.2.dist-info/WHEEL
parc_checker_core-1.2.dist-info/top_level.txt
parc_checker_core-1.2.dist-info/RECORD
