Metadata-Version: 2.1
Name: parc-checker-core
Version: 1.2
Summary: PARC Checker core library
Home-page: UNKNOWN
Author: Dovydas Jančauskas
Author-email: dovydasjan@gmail.com
License: UNKNOWN
Platform: UNKNOWN
Requires-Dist: parallel-executor (==1.1)
Provides-Extra: dev
Requires-Dist: pytest ; extra == 'dev'
Requires-Dist: pytest-cov ; extra == 'dev'
